spclustering-0.8.0.dist-info/LICENSE
spclustering-0.8.0.dist-info/WHEEL
spclustering-0.8.0.dist-info/top_level.txt
spclustering-0.8.0.dist-info/RECORD
spclustering-0.8.0.dist-info/METADATA
spclustering/io.c
spclustering/RaggedArray.h
spclustering/spc.py
spclustering/SW.c
spclustering/timer.c
spclustering/timer.h
spclustering/spclib.so
spclustering/Makefile
spclustering/__init__.py
spclustering/aux2.c
spclustering/param.h
spclustering/SW.h
spclustering/utilities.h
spclustering/utilities.c
spclustering/param.c
spclustering/spclib.c
spclustering/RaggedArray.c
spclustering/aux1.c
spclustering/edge.c
spclustering/distance.c
