Metadata-Version: 2.1
Name: spclustering
Version: 0.8.0
Summary: Python Wrapper for Superparamagnetic Clustering
Home-page: https://github.com/ferchaure/SPC/
Author: Fernando Julian Chaure
Author-email: fchaure@fi.uba.ar
Keywords: clustering
Classifier: Programming Language :: Python :: 3
Classifier: License :: OSI Approved :: MIT License
Classifier: Operating System :: OS Independent
License-File: LICENSE
Requires-Dist: numpy
Requires-Dist: matplotlib
